lhcbdiracx/db/__init__.py
lhcbdiracx/db/py.typed
lhcbdiracx/db/sql/__init__.py
lhcbdiracx/db/sql/bookkeeping/__init__.py
lhcbdiracx/db/sql/bookkeeping/bk_types.py
lhcbdiracx/db/sql/bookkeeping/db.py
lhcbdiracx/db/sql/bookkeeping/functions.py
lhcbdiracx/db/sql/bookkeeping/models.py
lhcbdiracx/db/sql/bookkeeping/queries.py
lhcbdiracx/db/sql/bookkeeping/schema.py
lhcbdiracx_db-0.0.7.dist-info/METADATA
lhcbdiracx_db-0.0.7.dist-info/WHEEL
lhcbdiracx_db-0.0.7.dist-info/entry_points.txt
lhcbdiracx_db-0.0.7.dist-info/top_level.txt
lhcbdiracx_db-0.0.7.dist-info/RECORD
